LICENSE
MANIFEST.in
setup.cfg
setup.py
streamlit_stepper_bar/__init__.py
streamlit_stepper_bar/version.py
streamlit_stepper_bar.egg-info/PKG-INFO
streamlit_stepper_bar.egg-info/SOURCES.txt
streamlit_stepper_bar.egg-info/dependency_links.txt
streamlit_stepper_bar.egg-info/requires.txt
streamlit_stepper_bar.egg-info/top_level.txt
streamlit_stepper_bar/streamlit_stepper_bar_horizontal/__init__.py
streamlit_stepper_bar/streamlit_stepper_bar_horizontal/frontend/build/asset-manifest.json
streamlit_stepper_bar/streamlit_stepper_bar_horizontal/frontend/build/bootstrap.min.css
streamlit_stepper_bar/streamlit_stepper_bar_horizontal/frontend/build/index.html
streamlit_stepper_bar/streamlit_stepper_bar_horizontal/frontend/build/static/js/2.bf0f749d.chunk.js
streamlit_stepper_bar/streamlit_stepper_bar_horizontal/frontend/build/static/js/2.bf0f749d.chunk.js.LICENSE.txt
streamlit_stepper_bar/streamlit_stepper_bar_horizontal/frontend/build/static/js/2.bf0f749d.chunk.js.map
streamlit_stepper_bar/streamlit_stepper_bar_horizontal/frontend/build/static/js/main.ba993a53.chunk.js
streamlit_stepper_bar/streamlit_stepper_bar_horizontal/frontend/build/static/js/main.ba993a53.chunk.js.map
streamlit_stepper_bar/streamlit_stepper_bar_horizontal/frontend/build/static/js/runtime-main.8340dc57.js
streamlit_stepper_bar/streamlit_stepper_bar_horizontal/frontend/build/static/js/runtime-main.8340dc57.js.map
streamlit_stepper_bar/streamlit_stepper_bar_vertical/__init__.py
streamlit_stepper_bar/streamlit_stepper_bar_vertical/frontend/build/asset-manifest.json
streamlit_stepper_bar/streamlit_stepper_bar_vertical/frontend/build/bootstrap.min.css
streamlit_stepper_bar/streamlit_stepper_bar_vertical/frontend/build/index.html
streamlit_stepper_bar/streamlit_stepper_bar_vertical/frontend/build/static/js/2.9b490504.chunk.js
streamlit_stepper_bar/streamlit_stepper_bar_vertical/frontend/build/static/js/2.9b490504.chunk.js.LICENSE.txt
streamlit_stepper_bar/streamlit_stepper_bar_vertical/frontend/build/static/js/2.9b490504.chunk.js.map
streamlit_stepper_bar/streamlit_stepper_bar_vertical/frontend/build/static/js/main.112912df.chunk.js
