Metadata-Version: 2.1
Name: streamlit-stepper-bar
Version: 0.0.8
Summary: A MaterialUI stepper bar based for Streamlit.
Home-page: https://github.com/BionomeeX/streamlit-stepper-bar
Author: Hadarak
License: MIT
Platform: UNKNOWN
Classifier: Programming Language :: Python :: 3
Classifier: License :: OSI Approved :: MIT License
Requires-Python: >=3.7
License-File: LICENSE
